README.md
pyproject.toml
wizard_domaininfo/__init__.py
wizard_domaininfo/__main__.py
wizard_domaininfo/airports.dat
wizard_domaininfo/cli.py
wizard_domaininfo/countries.dat
wizard_domaininfo/countries3.dat
wizard_domaininfo/domaininfo.py
wizard_domaininfo/net.py
wizard_domaininfo/parse.py
wizard_domaininfo/pwhois.py
wizard_domaininfo/shared.py
wizard_domaininfo/states_au.dat
wizard_domaininfo/states_ca.dat
wizard_domaininfo/states_us.dat
wizard_domaininfo/utils.py
wizard_domaininfo-0.2.6.dist-info/entry_points.txt
wizard_domaininfo-0.2.6.dist-info/LICENSE
wizard_domaininfo-0.2.6.dist-info/WHEEL
wizard_domaininfo-0.2.6.dist-info/METADATA
wizard_domaininfo-0.2.6.dist-info/RECORD
