Metadata-Version: 2.1
Name: wizard-domaininfo
Version: 0.2.6
Summary: DNS/Whois Domain Information library
Home-page: https://github.com/meramsey/wizard-domaininfo
License: MIT
Keywords: whois,nic,domain,dns,rdap
Author: Michael Ramsey
Author-email: mike@hackerdise.me
Requires-Python: >=3.6.1,<4.0.0
Classifier: License :: OSI Approved :: MIT License
Classifier: Programming Language :: Python :: 3
Classifier: Programming Language :: Python :: 3.10
Classifier: Programming Language :: Python :: 3.7
Classifier: Programming Language :: Python :: 3.8
Classifier: Programming Language :: Python :: 3.9
Provides-Extra: ipwhois
Requires-Dist: aiodns (>=3.0.0,<4.0.0)
Requires-Dist: atomicwrites (>=1.4.0,<2.0.0)
Requires-Dist: cached-property (>=1.5.2,<2.0.0)
Requires-Dist: contextvars (>=2.4,<3.0)
Requires-Dist: immutables (>=0.16,<0.17)
Requires-Dist: importlib-metadata (>=4.8.2,<5.0.0)
Requires-Dist: ipwhois (>=1.2.0,<2.0.0); extra == "ipwhois"
Requires-Dist: python-dateutil (>=2.8.2,<3.0.0)
Requires-Dist: requests (>=2.26.0,<3.0.0)
Requires-Dist: zipp (>=3.6.0,<4.0.0)
Project-URL: Repository, https://github.com/meramsey/wizard-domaininfo
